authme_api/__init__.py
authme_api/models.py
authme_api/hash_types/__init__.py
authme_api/hash_types/sha256.py
authme_api-0.1.6.dist-info/LICENSE
authme_api-0.1.6.dist-info/METADATA
authme_api-0.1.6.dist-info/WHEEL
authme_api-0.1.6.dist-info/top_level.txt
authme_api-0.1.6.dist-info/RECORD
