Metadata-Version: 2.1
Name: authme-api
Version: 0.1.6
Summary: MySQL API for AuthMe
Home-page: https://git.cofob.ru/cofob/authme_api
License: UNKNOWN
Platform: UNKNOWN
Requires-Python: >=3.6
License-File: LICENSE
Requires-Dist: mysql-connector-python
